{
	"configurations" : 
	[
		{
			"directories" : 
			[
				{
					"build" : ".",
					"childIndexes" : 
					[
						1
					],
					"jsonFile" : "directory-.-Debug-f5ebdc15457944623624.json",
					"minimumCMakeVersion" : 
					{
						"string" : "3.3"
					},
					"projectIndex" : 0,
					"source" : ".",
					"targetIndexes" : 
					[
						28
					]
				},
				{
					"build" : "check",
					"jsonFile" : "directory-check-Debug-a6171d59da8d6a8f1f50.json",
					"minimumCMakeVersion" : 
					{
						"string" : "3.3"
					},
					"parentIndex" : 0,
					"projectIndex" : 0,
					"source" : "check",
					"targetIndexes" : 
					[
						0,
						1,
						2,
						3,
						4,
						5,
						6,
						7,
						8,
						9,
						10,
						11,
						12,
						13,
						14,
						15,
						16,
						17,
						18,
						19,
						20,
						21,
						22,
						23,
						24,
						25,
						26,
						27
					]
				}
			],
			"name" : "Debug",
			"projects" : 
			[
				{
					"directoryIndexes" : 
					[
						0,
						1
					],
					"name" : "Binpacking",
					"targetIndexes" : 
					[
						0,
						1,
						2,
						3,
						4,
						5,
						6,
						7,
						8,
						9,
						10,
						11,
						12,
						13,
						14,
						15,
						16,
						17,
						18,
						19,
						20,
						21,
						22,
						23,
						24,
						25,
						26,
						27,
						28
					]
				}
			],
			"targets" : 
			[
				{
					"directoryIndex" : 1,
					"id" : "Continuous::@ff9eec1ed8bcfb1e1fcd",
					"jsonFile" : "target-Continuous-Debug-6f80a90b1ba891fd1fc1.json",
					"name" : "Continuous",
					"projectIndex" : 0
				},
				{
					"directoryIndex" : 1,
					"id" : "ContinuousBuild::@ff9eec1ed8bcfb1e1fcd",
					"jsonFile" : "target-ContinuousBuild-Debug-e7d8a8203b5793d69842.json",
					"name" : "ContinuousBuild",
					"projectIndex" : 0
				},
				{
					"directoryIndex" : 1,
					"id" : "ContinuousConfigure::@ff9eec1ed8bcfb1e1fcd",
					"jsonFile" : "target-ContinuousConfigure-Debug-0c4575c70e8fef5f8e93.json",
					"name" : "ContinuousConfigure",
					"projectIndex" : 0
				},
				{
					"directoryIndex" : 1,
					"id" : "ContinuousCoverage::@ff9eec1ed8bcfb1e1fcd",
					"jsonFile" : "target-ContinuousCoverage-Debug-8de569ea795cdba92782.json",
					"name" : "ContinuousCoverage",
					"projectIndex" : 0
				},
				{
					"directoryIndex" : 1,
					"id" : "ContinuousMemCheck::@ff9eec1ed8bcfb1e1fcd",
					"jsonFile" : "target-ContinuousMemCheck-Debug-6774d9408017d3640056.json",
					"name" : "ContinuousMemCheck",
					"projectIndex" : 0
				},
				{
					"directoryIndex" : 1,
					"id" : "ContinuousStart::@ff9eec1ed8bcfb1e1fcd",
					"jsonFile" : "target-ContinuousStart-Debug-4466291e99ad3f261eb0.json",
					"name" : "ContinuousStart",
					"projectIndex" : 0
				},
				{
					"directoryIndex" : 1,
					"id" : "ContinuousSubmit::@ff9eec1ed8bcfb1e1fcd",
					"jsonFile" : "target-ContinuousSubmit-Debug-5ee41086d230994d4e73.json",
					"name" : "ContinuousSubmit",
					"projectIndex" : 0
				},
				{
					"directoryIndex" : 1,
					"id" : "ContinuousTest::@ff9eec1ed8bcfb1e1fcd",
					"jsonFile" : "target-ContinuousTest-Debug-d26f52cdf8af5f218a58.json",
					"name" : "ContinuousTest",
					"projectIndex" : 0
				},
				{
					"directoryIndex" : 1,
					"id" : "ContinuousUpdate::@ff9eec1ed8bcfb1e1fcd",
					"jsonFile" : "target-ContinuousUpdate-Debug-fe3c10916d95150d6049.json",
					"name" : "ContinuousUpdate",
					"projectIndex" : 0
				},
				{
					"directoryIndex" : 1,
					"id" : "Experimental::@ff9eec1ed8bcfb1e1fcd",
					"jsonFile" : "target-Experimental-Debug-89c3e37f4b72acfed1ea.json",
					"name" : "Experimental",
					"projectIndex" : 0
				},
				{
					"directoryIndex" : 1,
					"id" : "ExperimentalBuild::@ff9eec1ed8bcfb1e1fcd",
					"jsonFile" : "target-ExperimentalBuild-Debug-0423b5dcd9cb2ddd042a.json",
					"name" : "ExperimentalBuild",
					"projectIndex" : 0
				},
				{
					"directoryIndex" : 1,
					"id" : "ExperimentalConfigure::@ff9eec1ed8bcfb1e1fcd",
					"jsonFile" : "target-ExperimentalConfigure-Debug-6844062dc95616bb0e4e.json",
					"name" : "ExperimentalConfigure",
					"projectIndex" : 0
				},
				{
					"directoryIndex" : 1,
					"id" : "ExperimentalCoverage::@ff9eec1ed8bcfb1e1fcd",
					"jsonFile" : "target-ExperimentalCoverage-Debug-804434a4991f8926a92c.json",
					"name" : "ExperimentalCoverage",
					"projectIndex" : 0
				},
				{
					"directoryIndex" : 1,
					"id" : "ExperimentalMemCheck::@ff9eec1ed8bcfb1e1fcd",
					"jsonFile" : "target-ExperimentalMemCheck-Debug-27254adf63c69fcdbcbb.json",
					"name" : "ExperimentalMemCheck",
					"projectIndex" : 0
				},
				{
					"directoryIndex" : 1,
					"id" : "ExperimentalStart::@ff9eec1ed8bcfb1e1fcd",
					"jsonFile" : "target-ExperimentalStart-Debug-b9fcb9af4f17077620a7.json",
					"name" : "ExperimentalStart",
					"projectIndex" : 0
				},
				{
					"directoryIndex" : 1,
					"id" : "ExperimentalSubmit::@ff9eec1ed8bcfb1e1fcd",
					"jsonFile" : "target-ExperimentalSubmit-Debug-f583aa64c0d051124dd3.json",
					"name" : "ExperimentalSubmit",
					"projectIndex" : 0
				},
				{
					"directoryIndex" : 1,
					"id" : "ExperimentalTest::@ff9eec1ed8bcfb1e1fcd",
					"jsonFile" : "target-ExperimentalTest-Debug-9d2e8c57de35d268156e.json",
					"name" : "ExperimentalTest",
					"projectIndex" : 0
				},
				{
					"directoryIndex" : 1,
					"id" : "ExperimentalUpdate::@ff9eec1ed8bcfb1e1fcd",
					"jsonFile" : "target-ExperimentalUpdate-Debug-0ce1d0e4c4ba03a1ed00.json",
					"name" : "ExperimentalUpdate",
					"projectIndex" : 0
				},
				{
					"directoryIndex" : 1,
					"id" : "Nightly::@ff9eec1ed8bcfb1e1fcd",
					"jsonFile" : "target-Nightly-Debug-3c86bcb1f73aae2aacaf.json",
					"name" : "Nightly",
					"projectIndex" : 0
				},
				{
					"directoryIndex" : 1,
					"id" : "NightlyBuild::@ff9eec1ed8bcfb1e1fcd",
					"jsonFile" : "target-NightlyBuild-Debug-99f36ebd175c1081f5bd.json",
					"name" : "NightlyBuild",
					"projectIndex" : 0
				},
				{
					"directoryIndex" : 1,
					"id" : "NightlyConfigure::@ff9eec1ed8bcfb1e1fcd",
					"jsonFile" : "target-NightlyConfigure-Debug-bdd3919898d9333faf67.json",
					"name" : "NightlyConfigure",
					"projectIndex" : 0
				},
				{
					"directoryIndex" : 1,
					"id" : "NightlyCoverage::@ff9eec1ed8bcfb1e1fcd",
					"jsonFile" : "target-NightlyCoverage-Debug-bc8848e5078ee4a2d2ea.json",
					"name" : "NightlyCoverage",
					"projectIndex" : 0
				},
				{
					"directoryIndex" : 1,
					"id" : "NightlyMemCheck::@ff9eec1ed8bcfb1e1fcd",
					"jsonFile" : "target-NightlyMemCheck-Debug-880a33662348bebc442e.json",
					"name" : "NightlyMemCheck",
					"projectIndex" : 0
				},
				{
					"directoryIndex" : 1,
					"id" : "NightlyMemoryCheck::@ff9eec1ed8bcfb1e1fcd",
					"jsonFile" : "target-NightlyMemoryCheck-Debug-6c5c7f05eb45688176b4.json",
					"name" : "NightlyMemoryCheck",
					"projectIndex" : 0
				},
				{
					"directoryIndex" : 1,
					"id" : "NightlyStart::@ff9eec1ed8bcfb1e1fcd",
					"jsonFile" : "target-NightlyStart-Debug-1987f5babecb07853d35.json",
					"name" : "NightlyStart",
					"projectIndex" : 0
				},
				{
					"directoryIndex" : 1,
					"id" : "NightlySubmit::@ff9eec1ed8bcfb1e1fcd",
					"jsonFile" : "target-NightlySubmit-Debug-d5e90ff7f9d73424fdda.json",
					"name" : "NightlySubmit",
					"projectIndex" : 0
				},
				{
					"directoryIndex" : 1,
					"id" : "NightlyTest::@ff9eec1ed8bcfb1e1fcd",
					"jsonFile" : "target-NightlyTest-Debug-5dd1e16d28db8f1bd176.json",
					"name" : "NightlyTest",
					"projectIndex" : 0
				},
				{
					"directoryIndex" : 1,
					"id" : "NightlyUpdate::@ff9eec1ed8bcfb1e1fcd",
					"jsonFile" : "target-NightlyUpdate-Debug-46dc0c39f4e11cc01c3b.json",
					"name" : "NightlyUpdate",
					"projectIndex" : 0
				},
				{
					"directoryIndex" : 0,
					"id" : "binpacking::@6890427a1f51a3e7e1df",
					"jsonFile" : "target-binpacking-Debug-9de5b3e50f3d53d5db29.json",
					"name" : "binpacking",
					"projectIndex" : 0
				}
			]
		}
	],
	"kind" : "codemodel",
	"paths" : 
	{
		"build" : "/home/roderich/Documents/BAP/gitdir01/dwdforflowshops/build",
		"source" : "/home/roderich/Documents/BAP/gitdir01/dwdforflowshops"
	},
	"version" : 
	{
		"major" : 2,
		"minor" : 3
	}
}
